heconsole/__init__.py
heconsole/heconsole.py
heconsole-1.0.6.dist-info/WHEEL
heconsole-1.0.6.dist-info/METADATA
heconsole-1.0.6.dist-info/RECORD
