Metadata-Version: 2.1
Name: heconsole
Version: 1.0.6
Summary: Docs: https://github.com/mishakorzik/heconsole
License: MIT
Author: MishaKorzhik_He1Zen
Author-email: miguardzecurity@gmail.com
Requires-Python: >=3.6,<4.0
Classifier: License :: OSI Approved :: MIT License
Classifier: Programming Language :: Python :: 3
Classifier: Programming Language :: Python :: 3.10
Classifier: Programming Language :: Python :: 3.6
Classifier: Programming Language :: Python :: 3.7
Classifier: Programming Language :: Python :: 3.8
Classifier: Programming Language :: Python :: 3.9
